uni_text/__init__.py
uni_text/uni_text.py
uni_text-1.0.0.dist-info/licenses/LICENSE
uni_text-1.0.0.dist-info/METADATA
uni_text-1.0.0.dist-info/WHEEL
uni_text-1.0.0.dist-info/top_level.txt
uni_text-1.0.0.dist-info/RECORD
