Metadata-Version: 2.4
Name: uni-text
Version: 1.0.0
Summary: A Python library for Unicode text processing, including punctuation handling and CJK character detection
License: MIT
Project-URL: Homepage, https://github.com/speech2srt/uni-text
Project-URL: Repository, https://github.com/speech2srt/uni-text
Project-URL: Issues, https://github.com/speech2srt/uni-text/issues
Requires-Python: >=3.10
License-File: LICENSE
Dynamic: license-file
